ocrd_typegroups_classifier/__init__.py
ocrd_typegroups_classifier/constants.py
ocrd_typegroups_classifier/ocrd-tool.json
ocrd_typegroups_classifier/processor.py
ocrd_typegroups_classifier/typegroups_classifier.py
ocrd_typegroups_classifier/cli/__init__.py
ocrd_typegroups_classifier/cli/ocrd_cli.py
ocrd_typegroups_classifier/cli/simple.py
ocrd_typegroups_classifier/data/__init__.py
ocrd_typegroups_classifier/data/binarization.py
ocrd_typegroups_classifier/data/classmap.py
ocrd_typegroups_classifier/data/qloss.py
ocrd_typegroups_classifier/models/__init__.py
ocrd_typegroups_classifier/models/colwise_classifier.tgc
ocrd_typegroups_classifier/models/densenet121.tgc
ocrd_typegroups_classifier/network/__init__.py
ocrd_typegroups_classifier/network/col_classifier.py
ocrd_typegroups_classifier/network/densenet.py
ocrd_typegroups_classifier/network/dontcareloss.py
ocrd_typegroups_classifier/network/resnet.py
ocrd_typegroups_classifier/network/var_conv2d.py
ocrd_typegroups_classifier/network/vgg.py
ocrd_typegroups_classifier/network/vraec.py
ocrd_typegroups_classifier-0.5.0.dist-info/LICENSE
ocrd_typegroups_classifier-0.5.0.dist-info/METADATA
ocrd_typegroups_classifier-0.5.0.dist-info/WHEEL
ocrd_typegroups_classifier-0.5.0.dist-info/entry_points.txt
ocrd_typegroups_classifier-0.5.0.dist-info/top_level.txt
ocrd_typegroups_classifier-0.5.0.dist-info/RECORD
