Metadata-Version: 2.1
Name: ocrd-typegroups-classifier
Version: 0.5.0
Summary: Typegroups classifier for OCR
Home-page: https://github.com/OCR-D/ocrd_typegroups_classifier
Author: Matthias Seuret, Konstantin Baierer
Author-email: seuretm@users.noreply.github.com
License: Apache License 2.0
License-File: LICENSE
Requires-Dist: ocrd (>=2.22.3)
Requires-Dist: pandas
Requires-Dist: scikit-image
Requires-Dist: torch (>=1.4.0)
Requires-Dist: torchvision (>=0.5.0)
